mcp_refcache/__init__.py
mcp_refcache/cache.py
mcp_refcache/context.py
mcp_refcache/context_integration.py
mcp_refcache/models.py
mcp_refcache/permissions.py
mcp_refcache/preview.py
mcp_refcache/py.typed
mcp_refcache/resolution.py
mcp_refcache/access/__init__.py
mcp_refcache/access/actor.py
mcp_refcache/access/checker.py
mcp_refcache/access/namespace.py
mcp_refcache/backends/__init__.py
mcp_refcache/backends/base.py
mcp_refcache/backends/memory.py
mcp_refcache/backends/redis.py
mcp_refcache/backends/sqlite.py
mcp_refcache/backends/task_base.py
mcp_refcache/backends/task_memory.py
mcp_refcache/fastmcp/__init__.py
mcp_refcache/fastmcp/admin_tools.py
mcp_refcache/fastmcp/instructions.py
mcp_refcache-0.2.0.dist-info/METADATA
mcp_refcache-0.2.0.dist-info/WHEEL
mcp_refcache-0.2.0.dist-info/licenses/LICENSE
mcp_refcache-0.2.0.dist-info/RECORD
