Metadata-Version: 2.4
Name: mcp-refcache
Version: 0.2.0
Summary: Reference-based caching for FastMCP servers with namespace isolation, access control, and private computation support
Author-email: l4b4r4b4b4 <lucas.cansino@mail.de>
License: MIT
License-File: LICENSE
Keywords: access-control,agent,cache,context,fastmcp,llm,mcp,namespaces,reference
Classifier: Development Status :: 3 - Alpha
Classifier: Intended Audience :: Developers
Classifier: License :: OSI Approved :: MIT License
Classifier: Programming Language :: Python :: 3.10
Classifier: Programming Language :: Python :: 3.11
Classifier: Programming Language :: Python :: 3.12
Classifier: Programming Language :: Python :: 3.13
Classifier: Topic :: Scientific/Engineering :: Artificial Intelligence
Classifier: Topic :: Software Development :: Libraries :: Python Modules
Classifier: Typing :: Typed
Requires-Python: >=3.10
Requires-Dist: pydantic>=2.0.0
Provides-Extra: all
Requires-Dist: fastmcp>=2.0.0; extra == 'all'
Requires-Dist: langfuse>=3.10.5; extra == 'all'
Requires-Dist: redis>=7.0.0; extra == 'all'
Requires-Dist: tiktoken>=0.5.0; extra == 'all'
Requires-Dist: transformers>=4.30.0; extra == 'all'
Provides-Extra: langfuse
Requires-Dist: langfuse>=3.10.5; extra == 'langfuse'
Provides-Extra: mcp
Requires-Dist: fastmcp>=2.0.0; extra == 'mcp'
Provides-Extra: redis
Requires-Dist: redis>=7.0.0; extra == 'redis'
Provides-Extra: server
Requires-Dist: fastmcp>=2.0.0; extra == 'server'
Requires-Dist: langfuse>=3.10.5; extra == 'server'
Requires-Dist: redis>=7.0.0; extra == 'server'
Provides-Extra: tiktoken
Requires-Dist: tiktoken>=0.5.0; extra == 'tiktoken'
Provides-Extra: transformers
Requires-Dist: transformers>=4.30.0; extra == 'transformers'
